fluentcms_socialfeed/__init__.py
fluentcms_socialfeed/content_plugins.py
fluentcms_socialfeed/models.py
fluentcms_socialfeed/locale/ru/LC_MESSAGES/django.mo
fluentcms_socialfeed/migrations/0001_initial.py
fluentcms_socialfeed/migrations/__init__.py
fluentcms_socialfeed/templates/fluentcms_socialfeed/socialfeed.html
fluentcms_socialfeed-1.0.0.dist-info/DESCRIPTION.rst
fluentcms_socialfeed-1.0.0.dist-info/METADATA
fluentcms_socialfeed-1.0.0.dist-info/RECORD
fluentcms_socialfeed-1.0.0.dist-info/WHEEL
fluentcms_socialfeed-1.0.0.dist-info/metadata.json
fluentcms_socialfeed-1.0.0.dist-info/top_level.txt
